{
  "indexes": [
    {
      "collectionGroup": "categories",
      "queryScope": "COLLECTION",
      "fields": [
        { "fieldPath": "mates", "arrayConfig": "CONTAINS" },
        { "fieldPath": "createdAt", "order": "DESCENDING" },
        { "fieldPath": "__name__", "order": "DESCENDING" }
      ]
    },
    {
      "collectionGroup": "categories",
      "queryScope": "COLLECTION",
      "fields": [
        { "fieldPath": "mates", "arrayConfig": "CONTAINS" },
        { "fieldPath": "name", "order": "ASCENDING" },
        { "fieldPath": "__name__", "order": "ASCENDING" }
      ]
    },
    {
      "collectionGroup": "categories",
      "queryScope": "COLLECTION",
      "fields": [
        { "fieldPath": "userId", "order": "ASCENDING" },
        { "fieldPath": "createdAt", "order": "DESCENDING" },
        { "fieldPath": "__name__", "order": "DESCENDING" }
      ]
    },
    {
      "collectionGroup": "comment_records",
      "queryScope": "COLLECTION",
      "fields": [
        { "fieldPath": "isDeleted", "order": "ASCENDING" },
        { "fieldPath": "photoId", "order": "ASCENDING" },
        { "fieldPath": "createdAt", "order": "ASCENDING" },
        { "fieldPath": "__name__", "order": "ASCENDING" }
      ]
    },
    {
      "collectionGroup": "friend_requests",
      "queryScope": "COLLECTION",
      "fields": [
        { "fieldPath": "fromUserId", "order": "ASCENDING" },
        { "fieldPath": "status", "order": "ASCENDING" },
        { "fieldPath": "createdAt", "order": "DESCENDING" },
        { "fieldPath": "__name__", "order": "DESCENDING" }
      ]
    },
    {
      "collectionGroup": "friend_requests",
      "queryScope": "COLLECTION",
      "fields": [
        { "fieldPath": "receiverUid", "order": "ASCENDING" },
        { "fieldPath": "status", "order": "ASCENDING" },
        { "fieldPath": "createdAt", "order": "DESCENDING" },
        { "fieldPath": "__name__", "order": "DESCENDING" }
      ]
    },
    {
      "collectionGroup": "friend_requests",
      "queryScope": "COLLECTION",
      "fields": [
        { "fieldPath": "senderUid", "order": "ASCENDING" },
        { "fieldPath": "status", "order": "ASCENDING" },
        { "fieldPath": "createdAt", "order": "DESCENDING" },
        { "fieldPath": "__name__", "order": "DESCENDING" }
      ]
    },
    {
      "collectionGroup": "friend_requests",
      "queryScope": "COLLECTION",
      "fields": [
        { "fieldPath": "status", "order": "ASCENDING" },
        { "fieldPath": "toUserId", "order": "ASCENDING" },
        { "fieldPath": "createdAt", "order": "DESCENDING" },
        { "fieldPath": "__name__", "order": "DESCENDING" }
      ]
    },
    {
      "collectionGroup": "friends",
      "queryScope": "COLLECTION",
      "fields": [
        { "fieldPath": "isActive", "order": "ASCENDING" },
        { "fieldPath": "becameFriendsAt", "order": "DESCENDING" },
        { "fieldPath": "__name__", "order": "DESCENDING" }
      ]
    },
    {
      "collectionGroup": "friends",
      "queryScope": "COLLECTION",
      "fields": [
        { "fieldPath": "isFavorite", "order": "ASCENDING" },
        { "fieldPath": "status", "order": "ASCENDING" },
        { "fieldPath": "addedAt", "order": "DESCENDING" },
        { "fieldPath": "__name__", "order": "DESCENDING" }
      ]
    },
    {
      "collectionGroup": "friends",
      "queryScope": "COLLECTION",
      "fields": [
        { "fieldPath": "status", "order": "ASCENDING" },
        { "fieldPath": "addedAt", "order": "DESCENDING" },
        { "fieldPath": "__name__", "order": "DESCENDING" }
      ]
    },
    {
      "collectionGroup": "friends",
      "queryScope": "COLLECTION",
      "fields": [
        { "fieldPath": "status", "order": "ASCENDING" },
        { "fieldPath": "createdAt", "order": "DESCENDING" },
        { "fieldPath": "__name__", "order": "DESCENDING" }
      ]
    },
    {
      "collectionGroup": "friends",
      "queryScope": "COLLECTION",
      "fields": [
        { "fieldPath": "status", "order": "ASCENDING" },
        { "fieldPath": "isFavorite", "order": "ASCENDING" },
        { "fieldPath": "createdAt", "order": "DESCENDING" },
        { "fieldPath": "__name__", "order": "DESCENDING" }
      ]
    },
    {
      "collectionGroup": "friends",
      "queryScope": "COLLECTION",
      "fields": [
        { "fieldPath": "status", "order": "ASCENDING" },
        { "fieldPath": "type", "order": "ASCENDING" },
        { "fieldPath": "createdAt", "order": "DESCENDING" },
        { "fieldPath": "__name__", "order": "DESCENDING" }
      ]
    },
    {
      "collectionGroup": "notifications",
      "queryScope": "COLLECTION",
      "fields": [
        { "fieldPath": "recipientUserId", "order": "ASCENDING" },
        { "fieldPath": "createdAt", "order": "ASCENDING" },
        { "fieldPath": "__name__", "order": "ASCENDING" }
      ]
    },
    {
      "collectionGroup": "notifications",
      "queryScope": "COLLECTION",
      "fields": [
        { "fieldPath": "recipientUserId", "order": "ASCENDING" },
        { "fieldPath": "createdAt", "order": "DESCENDING" },
        { "fieldPath": "__name__", "order": "DESCENDING" }
      ]
    },
    {
      "collectionGroup": "photos",
      "queryScope": "COLLECTION",
      "fields": [
        { "fieldPath": "status", "order": "ASCENDING" },
        { "fieldPath": "createdAt", "order": "DESCENDING" },
        { "fieldPath": "__name__", "order": "DESCENDING" }
      ]
    },
    {
      "collectionGroup": "photos",
      "queryScope": "COLLECTION",
      "fields": [
        { "fieldPath": "status", "order": "ASCENDING" },
        { "fieldPath": "deletedAt", "order": "DESCENDING" },
        { "fieldPath": "__name__", "order": "DESCENDING" }
      ]
    },
    {
      "collectionGroup": "photos",
      "queryScope": "COLLECTION",
      "fields": [
        { "fieldPath": "status", "order": "ASCENDING" },
        { "fieldPath": "unactive", "order": "ASCENDING" },
        { "fieldPath": "createdAt", "order": "DESCENDING" },
        { "fieldPath": "__name__", "order": "DESCENDING" }
      ]
    },
    {
      "collectionGroup": "photos",
      "queryScope": "COLLECTION",
      "fields": [
        { "fieldPath": "storageType", "order": "ASCENDING" },
        { "fieldPath": "uploadStatusImage", "order": "ASCENDING" },
        { "fieldPath": "createdAt", "order": "DESCENDING" },
        { "fieldPath": "__name__", "order": "DESCENDING" }
      ]
    },
    {
      "collectionGroup": "photos",
      "queryScope": "COLLECTION",
      "fields": [
        { "fieldPath": "unactive", "order": "ASCENDING" },
        { "fieldPath": "createdAt", "order": "DESCENDING" },
        { "fieldPath": "__name__", "order": "DESCENDING" }
      ]
    }
  ],
  "fieldOverrides": [
    {
      "collectionGroup": "photos",
      "fieldPath": "userID",
      "ttl": false,
      "indexes": [
        {
          "order": "ASCENDING",
          "queryScope": "COLLECTION"
        },
        {
          "order": "DESCENDING",
          "queryScope": "COLLECTION"
        },
        {
          "arrayConfig": "CONTAINS",
          "queryScope": "COLLECTION"
        },
        {
          "order": "ASCENDING",
          "queryScope": "COLLECTION_GROUP"
        }
      ]
    }
  ]
}